nonebot/adapters/heybox/__init__.py
nonebot/adapters/heybox/adapter.py
nonebot/adapters/heybox/bot.py
nonebot/adapters/heybox/config.py
nonebot/adapters/heybox/event.py
nonebot/adapters/heybox/exception.py
nonebot/adapters/heybox/message.py
nonebot/adapters/heybox/model.py
nonebot/adapters/heybox/utils.py
nonebot_adapter_heybox-0.1.1.dist-info/LICENSE
nonebot_adapter_heybox-0.1.1.dist-info/METADATA
nonebot_adapter_heybox-0.1.1.dist-info/WHEEL
nonebot_adapter_heybox-0.1.1.dist-info/top_level.txt
nonebot_adapter_heybox-0.1.1.dist-info/RECORD
