Metadata-Version: 2.2
Name: nonebot-adapter-heybox
Version: 0.1.1
Summary: heybox adapter for nonebot2
Author-email: hzw223 <614867321@qq.com>
Project-URL: Homepage, https://github.com/lclbm/adapter-heybox
Project-URL: Issues, https://github.com/lclbm/adapter-heybox/issues
Classifier: Development Status :: 5 - Production/Stable
Classifier: Framework :: Robot Framework
Classifier: Framework :: Robot Framework :: Library
Classifier: Operating System :: OS Independent
Classifier: Programming Language :: Python :: 3
Requires-Python: >=3.11
License-File: LICENSE
Requires-Dist: nonebot2>=2.0.0
